psqlmodule/__init__.py
psqlmodule/config.yaml
psqlmodule/find_levelled_master_table_list.py
psqlmodule/get_schema.py
psqlmodule/gitmodule.py
psqlmodule/inputmodule.py
psqlmodule/logger.py
psqlmodule/ps.py
psqlmodule/psqlmodule.py
psqlmodule/text_color.py
psqlmodule/transfer.py
psqlmodule-0.1.6.dist-info/METADATA
psqlmodule-0.1.6.dist-info/WHEEL
psqlmodule-0.1.6.dist-info/top_level.txt
psqlmodule-0.1.6.dist-info/RECORD
